banweb/__init__.py
banweb-0.1.0.dist-info/LICENSE
banweb-0.1.0.dist-info/METADATA
banweb-0.1.0.dist-info/WHEEL
banweb-0.1.0.dist-info/top_level.txt
banweb-0.1.0.dist-info/RECORD
