Metadata-Version: 2.1
Name: banweb
Version: 0.1.0
Summary: Interface with the banner website to access academic information
Home-page: https://github.com/Alex979/banweb-python
License: MIT
Platform: UNKNOWN
Classifier: Programming Language :: Python :: 3
Classifier: License :: OSI Approved :: MIT License
Classifier: Operating System :: OS Independent
Requires-Dist: requests
Requires-Dist: beautifulsoup4
